pytest_revealtype_injector/__init__.py
pytest_revealtype_injector/hooks.py
pytest_revealtype_injector/log.py
pytest_revealtype_injector/main.py
pytest_revealtype_injector/models.py
pytest_revealtype_injector/plugin.py
pytest_revealtype_injector/py.typed
pytest_revealtype_injector/adapter/__init__.py
pytest_revealtype_injector/adapter/basedpyright_.py
pytest_revealtype_injector/adapter/mypy_.py
pytest_revealtype_injector/adapter/pyrefly_.py
pytest_revealtype_injector/adapter/pyright_.py
pytest_revealtype_injector/adapter/ty_.py
pytest_revealtype_injector-0.8.0.dist-info/METADATA
pytest_revealtype_injector-0.8.0.dist-info/WHEEL
pytest_revealtype_injector-0.8.0.dist-info/entry_points.txt
pytest_revealtype_injector-0.8.0.dist-info/licenses/COPYING.mit
pytest_revealtype_injector-0.8.0.dist-info/RECORD
