Metadata-Version: 2.4
Name: pytest-revealtype-injector
Version: 0.8.0
Summary: Pytest plugin for replacing reveal_type() calls inside test functions with static and runtime type checking result comparison, for confirming type annotation validity.
Project-URL: homepage, https://github.com/abelcheung/pytest-revealtype-injector
Author-email: Abel Cheung <abelcheung@gmail.com>
License-Expression: MIT
License-File: COPYING.mit
Keywords: annotation,dynamic-typing,pytest,reveal_type,static-typing,stub,stubs,type-checking,types,typing
Classifier: Development Status :: 4 - Beta
Classifier: Framework :: Pytest
Classifier: Intended Audience :: Developers
Classifier: Programming Language :: Python
Classifier: Programming Language :: Python :: 3
Classifier: Programming Language :: Python :: 3 :: Only
Classifier: Programming Language :: Python :: 3.10
Classifier: Programming Language :: Python :: 3.11
Classifier: Programming Language :: Python :: 3.12
Classifier: Programming Language :: Python :: 3.13
Classifier: Programming Language :: Python :: 3.14
Classifier: Topic :: Software Development :: Testing
Classifier: Typing :: Typed
Requires-Python: >=3.10
Requires-Dist: pytest>=7.0
Requires-Dist: schema>=0.7.8
Requires-Dist: typeguard>=4.3
Requires-Dist: typing-extensions>=4.0; python_version < '3.11'
